{
  "meta": {
    "theme": "Podmořský svět",
    "date": "2026-01-08",
    "width": 16,
    "height": 16
  },
  "grid": [
    [
      "O",
      "#",
      "#",
      "E",
      "#",
      "K",
      "#",
      "I",
      "#",
      "#",
      "#",
      "P",
      "#",
      "Č",
      "#",
      "#"
    ],
    [
      "C",
      "#",
      "#",
      "F",
      "#",
      "O",
      "#",
      "G",
      "#",
      "#",
      "#",
      "A",
      "#",
      "O",
      "#",
      "#"
    ],
    [
      "A",
      "#",
      "#",
      "E",
      "#",
      "U",
      "#",
      "L",
      "#",
      "#",
      "#",
      "M",
      "#",
      "K",
      "#",
      "#"
    ],
    [
      "S",
      "A",
      "R",
      "K",
      "A",
      "Z",
      "M",
      "U",
      "S",
      "#",
      "#",
      "Á",
      "#",
      "O",
      "#",
      "#"
    ],
    [
      "#",
      "#",
      "#",
      "T",
      "#",
      "L",
      "#",
      "#",
      "U",
      "Č",
      "I",
      "T",
      "E",
      "L",
      "#",
      "#"
    ],
    [
      "L",
      "#",
      "#",
      "#",
      "H",
      "O",
      "L",
      "U",
      "B",
      "#",
      "#",
      "K",
      "#",
      "Á",
      "#",
      "#"
    ],
    [
      "O",
      "#",
      "#",
      "T",
      "#",
      "#",
      "#",
      "#",
      "N",
      "Ě",
      "H",
      "A",
      "#",
      "D",
      "#",
      "#"
    ],
    [
      "K",
      "A",
      "T",
      "E",
      "D",
      "R",
      "Á",
      "L",
      "A",
      "#",
      "#",
      "#",
      "#",
      "A",
      "#",
      "#"
    ],
    [
      "O",
      "#",
      "#",
      "R",
      "#",
      "#",
      "#",
      "#",
      "U",
      "M",
      "Ě",
      "N",
      "Í",
      "#",
      "#",
      "#"
    ],
    [
      "M",
      "#",
      "#",
      "Č",
      "#",
      "#",
      "T",
      "Á",
      "T",
      "#",
      "#",
      "#",
      "#",
      "O",
      "#",
      "#"
    ],
    [
      "O",
      "#",
      "#",
      "#",
      "I",
      "#",
      "Ý",
      "#",
      "I",
      "N",
      "V",
      "E",
      "N",
      "C",
      "E",
      "#"
    ],
    [
      "T",
      "#",
      "#",
      "#",
      "M",
      "U",
      "D",
      "R",
      "C",
      "#",
      "#",
      "M",
      "#",
      "H",
      "#",
      "#"
    ],
    [
      "I",
      "#",
      "#",
      "#",
      "P",
      "#",
      "E",
      "#",
      "A",
      "Ž",
      "#",
      "I",
      "#",
      "R",
      "#",
      "#"
    ],
    [
      "V",
      "#",
      "#",
      "#",
      "U",
      "#",
      "N",
      "#",
      "#",
      "L",
      "#",
      "G",
      "#",
      "A",
      "#",
      "#"
    ],
    [
      "A",
      "#",
      "#",
      "#",
      "L",
      "#",
      "#",
      "#",
      "#",
      "U",
      "#",
      "R",
      "#",
      "N",
      "#",
      "#"
    ],
    [
      "#",
      "#",
      "#",
      "#",
      "S",
      "#",
      "#",
      "#",
      "#",
      "Č",
      "#",
      "A",
      "#",
      "A",
      "#",
      "#"
    ]
  ],
  "words": [
    {
      "number": 7,
      "word": "SARKAZMUS",
      "clue": "kousavý výsměch",
      "row": 3,
      "col": 0,
      "direction": "H"
    },
    {
      "number": 9,
      "word": "UČITEL",
      "clue": "pedagog",
      "row": 4,
      "col": 8,
      "direction": "H"
    },
    {
      "number": 11,
      "word": "HOLUB",
      "clue": "městský pták",
      "row": 5,
      "col": 4,
      "direction": "H"
    },
    {
      "number": 13,
      "word": "NĚHA",
      "clue": "jemnost",
      "row": 6,
      "col": 8,
      "direction": "H"
    },
    {
      "number": 14,
      "word": "KATEDRÁLA",
      "clue": "velký chrám",
      "row": 7,
      "col": 0,
      "direction": "H"
    },
    {
      "number": 15,
      "word": "UMĚNÍ",
      "clue": "tvorba",
      "row": 8,
      "col": 8,
      "direction": "H"
    },
    {
      "number": 16,
      "word": "TÁT",
      "clue": "měnit se v vodu (infinitiv)",
      "row": 9,
      "col": 6,
      "direction": "H"
    },
    {
      "number": 19,
      "word": "INVENCE",
      "clue": "vynalézavost, nápaditost",
      "row": 10,
      "col": 8,
      "direction": "H"
    },
    {
      "number": 21,
      "word": "MUDRC",
      "clue": "moudrý člověk",
      "row": 11,
      "col": 4,
      "direction": "H"
    },
    {
      "number": 22,
      "word": "AŽ",
      "clue": "spojka nebo částice (vyjadřující míru)",
      "row": 12,
      "col": 8,
      "direction": "H"
    },
    {
      "number": 6,
      "word": "ČOKOLÁDA",
      "clue": "sladkost z kakaa",
      "row": 0,
      "col": 13,
      "direction": "V"
    },
    {
      "number": 17,
      "word": "OCHRANA",
      "clue": "bezpečí",
      "row": 9,
      "col": 13,
      "direction": "V"
    },
    {
      "number": 4,
      "word": "IGLU",
      "clue": "sněžný dům",
      "row": 0,
      "col": 7,
      "direction": "V"
    },
    {
      "number": 2,
      "word": "EFEKT",
      "clue": "účinek",
      "row": 0,
      "col": 3,
      "direction": "V"
    },
    {
      "number": 12,
      "word": "TERČ",
      "clue": "místo, kde se může střílet",
      "row": 6,
      "col": 3,
      "direction": "V"
    },
    {
      "number": 16,
      "word": "TÝDEN",
      "clue": "7 dní",
      "row": 9,
      "col": 6,
      "direction": "V"
    },
    {
      "number": 5,
      "word": "PAMÁTKA",
      "clue": "vzpomínka",
      "row": 0,
      "col": 11,
      "direction": "V"
    },
    {
      "number": 20,
      "word": "EMIGRA",
      "clue": "vystěhovalec",
      "row": 10,
      "col": 11,
      "direction": "V"
    },
    {
      "number": 10,
      "word": "LOKOMOTIVA",
      "clue": "tahoun vlaku",
      "row": 5,
      "col": 0,
      "direction": "V"
    },
    {
      "number": 1,
      "word": "OCAS",
      "clue": "ohon",
      "row": 0,
      "col": 0,
      "direction": "V"
    },
    {
      "number": 23,
      "word": "ŽLUČ",
      "clue": "tuková tekutina tvořená v játrech",
      "row": 12,
      "col": 9,
      "direction": "V"
    },
    {
      "number": 18,
      "word": "IMPULS",
      "clue": "podnět",
      "row": 10,
      "col": 4,
      "direction": "V"
    },
    {
      "number": 3,
      "word": "KOUZLO",
      "clue": "čáry",
      "row": 0,
      "col": 5,
      "direction": "V"
    }
  ],
  "tajenka_mask": [
    [
      3,
      8
    ],
    [
      4,
      8
    ],
    [
      5,
      8
    ],
    [
      6,
      8
    ],
    [
      7,
      8
    ],
    [
      8,
      8
    ],
    [
      9,
      8
    ],
    [
      10,
      8
    ],
    [
      11,
      8
    ],
    [
      12,
      8
    ]
  ],
  "tajenka_clue": "Podmořský svět"
}